LICENSE
MANIFEST.in
README.md
pyproject.toml
setup.py
nanopy/__init__.py
nanopy/ext.c
nanopy/opencl_program.h
nanopy/rpc.py
nanopy.egg-info/PKG-INFO
nanopy.egg-info/SOURCES.txt
nanopy.egg-info/dependency_links.txt
nanopy.egg-info/requires.txt
nanopy.egg-info/top_level.txt
nanopy/blake2b/COPYING
nanopy/blake2b/README.md
nanopy/blake2b/neon/blake2-impl.h
nanopy/blake2b/neon/blake2.h
nanopy/blake2b/neon/blake2b-load-neon.h
nanopy/blake2b/neon/blake2b-round.h
nanopy/blake2b/neon/blake2b.c
nanopy/blake2b/ref/blake2-impl.h
nanopy/blake2b/ref/blake2.h
nanopy/blake2b/ref/blake2b.c
nanopy/blake2b/sse/blake2-config.h
nanopy/blake2b/sse/blake2-impl.h
nanopy/blake2b/sse/blake2.h
nanopy/blake2b/sse/blake2b-compress-avx2.h
nanopy/blake2b/sse/blake2b-load-avx2-simple.h
nanopy/blake2b/sse/blake2b-load-avx2.h
nanopy/blake2b/sse/blake2b-load-sse2.h
nanopy/blake2b/sse/blake2b-load-sse41.h
nanopy/blake2b/sse/blake2b-round.h
nanopy/blake2b/sse/blake2b.c
nanopy/ed25519-donna/curve25519-donna-32bit.h
nanopy/ed25519-donna/curve25519-donna-64bit.h
nanopy/ed25519-donna/curve25519-donna-helpers.h
nanopy/ed25519-donna/curve25519-donna-sse2.h
nanopy/ed25519-donna/ed25519-donna-32bit-sse2.h
nanopy/ed25519-donna/ed25519-donna-32bit-tables.h
nanopy/ed25519-donna/ed25519-donna-64bit-sse2.h
nanopy/ed25519-donna/ed25519-donna-64bit-tables.h
nanopy/ed25519-donna/ed25519-donna-64bit-x86-32bit.h
nanopy/ed25519-donna/ed25519-donna-64bit-x86.h
nanopy/ed25519-donna/ed25519-donna-basepoint-table.h
nanopy/ed25519-donna/ed25519-donna-batchverify.h
nanopy/ed25519-donna/ed25519-donna-impl-base.h
nanopy/ed25519-donna/ed25519-donna-impl-sse2.h
nanopy/ed25519-donna/ed25519-donna-portable-identify.h
nanopy/ed25519-donna/ed25519-donna-portable.h
nanopy/ed25519-donna/ed25519-donna.h
nanopy/ed25519-donna/ed25519-hash-custom.h
nanopy/ed25519-donna/ed25519-hash.h
nanopy/ed25519-donna/ed25519-randombytes-custom.h
nanopy/ed25519-donna/ed25519-randombytes.h
nanopy/ed25519-donna/ed25519.c
nanopy/ed25519-donna/ed25519.h
nanopy/ed25519-donna/modm-donna-32bit.h
nanopy/ed25519-donna/modm-donna-64bit.h
tests/test_nanopy.py